{"nodes": [{"id": "src_components_searchbox_tsx", "label": "SearchBox.tsx", "file_type": "code", "source_file": "src\\components\\SearchBox.tsx", "source_location": "L1"}, {"id": "searchbox_searchbox", "label": "SearchBox()", "file_type": "code", "source_file": "src\\components\\SearchBox.tsx", "source_location": "L14"}], "edges": [{"source": "src_components_searchbox_tsx", "target": "react_compiler_runtime", "relation": "imports_from", "confidence": "EXTRACTED", "source_file": "src\\components\\SearchBox.tsx", "source_location": "L1", "weight": 1.0}, {"source": "src_components_searchbox_tsx", "target": "react", "relation": "imports_from", "confidence": "EXTRACTED", "source_file": "src\\components\\SearchBox.tsx", "source_location": "L2", "weight": 1.0}, {"source": "src_components_searchbox_tsx", "target": "src_components_ink_ts", "relation": "imports_from", "confidence": "EXTRACTED", "source_file": "src\\components\\SearchBox.tsx", "source_location": "L3", "weight": 1.0}, {"source": "src_components_searchbox_tsx", "target": "searchbox_searchbox", "relation": "contains", "confidence": "EXTRACTED", "source_file": "src\\components\\SearchBox.tsx", "source_location": "L14", "weight": 1.0}], "raw_calls": [{"caller_nid": "searchbox_searchbox", "callee": "_c", "source_file": "src\\components\\SearchBox.tsx", "source_location": "L15"}, {"caller_nid": "searchbox_searchbox", "callee": "slice", "source_file": "src\\components\\SearchBox.tsx", "source_location": "L37"}]}